{
  "format_version": "1.20.10",
  "minecraft:recipe_shaped": {
    "description": {
      "identifier": "morelights:cherry_lamp_recipe_recipe"
    },
    "tags": ["crafting_table"],
    "pattern": [
      "S",
      "G",
      "S"
    ],
    "key": {
      "G": { "item": "minecraft:glowstone" },
      "S": { "item": "minecraft:cherry_slab" }
    },
    "unlock": [
      {
        "item": "minecraft:glowstone"
      }
    ],
    "result": {
      "item": "morelights:cherry_lamp",
      "count": 1
    }
  }
}